README.md
setup.py
stir/__init__.py
stir/server.py
stir/utils.py
stir.egg-info/PKG-INFO
stir.egg-info/SOURCES.txt
stir.egg-info/dependency_links.txt
stir.egg-info/requires.txt
stir.egg-info/top_level.txt
stir/scripts/stir
stir/scripts/stir