Metadata-Version: 1.1
Name: stir
Version: 0.0.1
Summary: A simple merging package manager for microservices
Home-page: https://github.com/nullism/stir
Author: Aaron Meier
Author-email: webgovernor@gmail.com
License: MIT
Platform: UNKNOWN
Provides: stir
